fonsim/__init__.py
fonsim/colors.py
fonsim/notice_beta.py
fonsim/components/__init__.py
fonsim/components/actuators.py
fonsim/components/circulartube_autodiff.py
fonsim/components/containers.py
fonsim/components/containers_autodiff.py
fonsim/components/dummy.py
fonsim/components/restrictors.py
fonsim/components/sources.py
fonsim/components/terminals.py
fonsim/components/valves.py
fonsim/constants/__init__.py
fonsim/constants/norm.py
fonsim/constants/physical.py
fonsim/conversion/__init__.py
fonsim/conversion/indexmatch.py
fonsim/core/__init__.py
fonsim/core/component.py
fonsim/core/node.py
fonsim/core/setnumpythreads.py
fonsim/core/simulation.py
fonsim/core/solver.py
fonsim/core/system.py
fonsim/core/terminal.py
fonsim/core/variable.py
fonsim/data/__init__.py
fonsim/data/curve.py
fonsim/data/dataseries.py
fonsim/data/interpolate.py
fonsim/data/pvcurve.py
fonsim/data/writeout.py
fonsim/fluid/__init__.py
fonsim/fluid/fallback.py
fonsim/fluid/fluid.py
fonsim/fluids/Bingham.py
fonsim/fluids/IdealCompressible.py
fonsim/fluids/IdealIncompressible.py
fonsim/fluids/__init__.py
fonsim/resources/Measurement_60mm_balloon_actuator_01.csv
fonsim/visual/__init__.py
fonsim/visual/plotting.py
fonsim/wave/__init__.py
fonsim/wave/custom.py
fonsim/wave/wave.py
fonsim-0.5.0.dist-info/LICENSE.txt
fonsim-0.5.0.dist-info/METADATA
fonsim-0.5.0.dist-info/WHEEL
fonsim-0.5.0.dist-info/top_level.txt
fonsim-0.5.0.dist-info/RECORD
