Metadata-Version: 2.1
Name: fonsim
Version: 0.5.0
Summary: Fluidic Object-Oriented Network Simulator
Home-page: http://fonsim.org
Author: Arne Baeyens, Bert Van Raemdonck
Author-email: info@fonsim.org
License: AGPLv3
Keywords: simulator,simulation,flow,fluids,fluidic,soft robot,soro,soft robotics,soft robots
Classifier: Development Status :: 4 - Beta
Classifier: Intended Audience :: Science/Research
Classifier: Intended Audience :: Education
Classifier: License :: OSI Approved :: GNU Affero General Public License v3
Classifier: Programming Language :: Python :: 3
Classifier: Topic :: Scientific/Engineering
Classifier: Operating System :: OS Independent
Requires-Python: >=3.8
License-File: LICENSE.txt
Requires-Dist: numpy
Requires-Dist: scipy
Requires-Dist: matplotlib
Requires-Dist: stringunitconverter
Requires-Dist: importlib-metadata
Requires-Dist: importlib-resources
Requires-Dist: tabulate
